data_qleaning/__init__.py
data_qleaning/prepocess.py
data_qleaning-0.1.dist-info/LICENSE.txt
data_qleaning-0.1.dist-info/METADATA
data_qleaning-0.1.dist-info/WHEEL
data_qleaning-0.1.dist-info/top_level.txt
data_qleaning-0.1.dist-info/RECORD
