Metadata-Version: 2.1
Name: data-qleaning
Version: 0.1
Summary: Data Cleaning
Author-email: namithamanjunath4@gmail.com
License: UNKNOWN
Platform: UNKNOWN
License-File: LICENSE.txt
